NetworkSubnetting/__init__.py
NetworkSubnetting/Functions/__init__.py
NetworkSubnetting/Functions/subneting.py
NetworkSubnetting/main.py
networksubnetting-0.1.0.dist-info/WHEEL
networksubnetting-0.1.0.dist-info/METADATA
networksubnetting-0.1.0.dist-info/RECORD
