Metadata-Version: 2.1
Name: networksubnetting
Version: 0.1.0
Summary: Proyecto bimestral de la materia de Python basico UTPL
Author: daburneo1
Author-email: davichov2013@gmail.com
Requires-Python: >=3.8,<4.0
Classifier: Programming Language :: Python :: 3
Classifier: Programming Language :: Python :: 3.10
Classifier: Programming Language :: Python :: 3.8
Classifier: Programming Language :: Python :: 3.9
Requires-Dist: ipaddress (>=1.0.23,<2.0.0)
